README.rst
setup.cfg
setup.py
SQLAlchemy_FullText_Search.egg-info/PKG-INFO
SQLAlchemy_FullText_Search.egg-info/SOURCES.txt
SQLAlchemy_FullText_Search.egg-info/dependency_links.txt
SQLAlchemy_FullText_Search.egg-info/not-zip-safe
SQLAlchemy_FullText_Search.egg-info/requires.txt
SQLAlchemy_FullText_Search.egg-info/top_level.txt
sqlalchemy_fulltext/__init__.py
sqlalchemy_fulltext/modes.py