Metadata-Version: 1.1
Name: SQLAlchemy-FullText-Search
Version: 0.3.0
Summary: Provide FullText for MYSQL & SQLAlchemy model
Home-page: https://github.com/mengzhuo/sqlalchemy-fulltext-search
Author: Meng Zhuo, Alejandro Mesa, Davide Marchi
Author-email: mengzhuo1203@gmail.com, alejom99@gmail.com, dvdmrc92@gmail.com
License: BSD
Platform: any
Classifier: Environment :: Web Environment
Classifier: Intended Audience :: Developers
Classifier: License :: OSI Approved :: BSD License
Classifier: Operating System :: OS Independent
Classifier: Programming Language :: Python :: 2.7
Classifier: Programming Language :: Python :: 3.4
Classifier: Programming Language :: Python :: 3.6
Classifier: Programming Language :: Python :: 3.8
Classifier: Topic :: Internet :: WWW/HTTP :: Dynamic Content
Classifier: Topic :: Software Development :: Libraries :: Python Modules
